sparkdesk/__init__.py
sparkdesk/async/__init__.py
sparkdesk/async/chat.py
sparkdesk/async/cli.py
sparkdesk/async/completion.py
sparkdesk/authentication.py
sparkdesk/chat.py
sparkdesk/chat_utils.py
sparkdesk/cli.py
sparkdesk/completion.py
sparkdesk/consts.py
sparkdesk-0.1.4.dist-info/METADATA
sparkdesk-0.1.4.dist-info/WHEEL
sparkdesk-0.1.4.dist-info/RECORD
