Metadata-Version: 2.1
Name: sparkdesk
Version: 0.1.4
Summary: 
Author: vicalloy
Author-email: zbirder@gmail.com
Requires-Python: >=3.8,<4.0
Classifier: Programming Language :: Python :: 3
Classifier: Programming Language :: Python :: 3.8
Classifier: Programming Language :: Python :: 3.9
Classifier: Programming Language :: Python :: 3.10
Classifier: Programming Language :: Python :: 3.11
Provides-Extra: cli
Requires-Dist: click (>=8.1.7,<9.0.0) ; extra == "cli"
Requires-Dist: websockets (>=11.0.3,<12.0.0)
